rxnemb/__init__.py
rxnemb/version.py
rxnemb/core/__init__.py
rxnemb/core/data.py
rxnemb/core/ext_feat.py
rxnemb/core/layer.py
rxnemb/core/model.py
rxnemb/core/rxn_emb.py
rxnemb/core/scheduler.py
rxnemb/core/train.py
rxnemb/core/utils.py
rxnemb/ex_utils/__init__.py
rxnemb/ex_utils/cls_visualize.py
rxnemb/ex_utils/ks_cluster.py
rxnemb/weights/latest/parameters.json
rxnemb/weights/latest/model/valid_checkpoint.pt
rxnemb-1.0.1.dist-info/licenses/LICENSE
rxnemb-1.0.1.dist-info/METADATA
rxnemb-1.0.1.dist-info/WHEEL
rxnemb-1.0.1.dist-info/top_level.txt
rxnemb-1.0.1.dist-info/RECORD
