Metadata-Version: 2.4
Name: rxnemb
Version: 1.0.1
Summary: A reaction-level embedding descriptor.
License-Expression: MIT
Project-URL: Homepage, https://github.com/yourusername/myproj
Project-URL: Repository, https://github.com/yourusername/myproj.git
Requires-Python: >=3.9
License-File: LICENSE
Requires-Dist: numpy
Requires-Dist: pandas
Requires-Dist: torch
Requires-Dist: torch_geometric
Requires-Dist: qqtools
Provides-Extra: cu118
Requires-Dist: torch==2.0.1+cu118; extra == "cu118"
Requires-Dist: torchvision==0.15.2+cu118; extra == "cu118"
Requires-Dist: torchaudio==2.0.2+cu118; extra == "cu118"
Provides-Extra: cu121
Requires-Dist: torch==2.2.1+cu121; extra == "cu121"
Requires-Dist: torchvision==0.16.1+cu121; extra == "cu121"
Requires-Dist: torchaudio==2.1.1+cu121; extra == "cu121"
Provides-Extra: cu124
Requires-Dist: torch==2.4.0+cu124; extra == "cu124"
Requires-Dist: torchvision==0.18.0+cu124; extra == "cu124"
Requires-Dist: torchaudio==2.3.0+cu124; extra == "cu124"
Dynamic: license-file
